LICENSE.md
README.md
beancount_rabobank/__init__.py
beancount_rabobank/rabobank.py
beancount_rabobank/rabobank_test.py
beancount_rabobank/test_files/CSV_A_20201231_162236.csv
beancount_rabobank/test_files/CSV_A_20201231_162236.csv.extract
beancount_rabobank/test_files/CSV_A_20201231_162236.csv.file_account
beancount_rabobank/test_files/CSV_A_20201231_162236.csv.file_date
beancount_rabobank/test_files/CSV_A_20201231_162236.csv.file_name
beancount_rabobank/test_files/CSV_A_20201231_162237.csv
beancount_rabobank/test_files/CSV_A_20201231_162237.csv.extract
beancount_rabobank/test_files/CSV_A_20201231_162237.csv.file_account
beancount_rabobank/test_files/CSV_A_20201231_162237.csv.file_date
beancount_rabobank/test_files/CSV_A_20201231_162237.csv.file_name
beancount_rabobank/test_files/CSV_A_NL00RABO1234567890_EUR_20220331_20220702.csv
beancount_rabobank/test_files/CSV_A_NL00RABO1234567890_EUR_20220331_20220702.csv.extract
beancount_rabobank/test_files/CSV_A_NL00RABO1234567890_EUR_20220331_20220702.csv.file_account
beancount_rabobank/test_files/CSV_A_NL00RABO1234567890_EUR_20220331_20220702.csv.file_date
beancount_rabobank/test_files/CSV_A_NL00RABO1234567890_EUR_20220331_20220702.csv.file_name
beancount_rabobank-0.4.0.dist-info/LICENSE.md
beancount_rabobank-0.4.0.dist-info/WHEEL
beancount_rabobank-0.4.0.dist-info/METADATA
beancount_rabobank-0.4.0.dist-info/RECORD
