Metadata-Version: 2.1
Name: beancount-rabobank
Version: 0.4.0
Summary: Beancount importer for Rabobank CSV exports
Home-page: https://github.com/mvaerle/beancount-rabobank
License: MIT
Keywords: banking,beancount,cli-accounting,finance
Author: Marijn van Aerle
Author-email: marijn.vanaerle@gmail.com
Requires-Python: >=3.9,<4.0
Classifier: License :: OSI Approved :: MIT License
Classifier: Programming Language :: Python :: 3
Classifier: Programming Language :: Python :: 3.10
Classifier: Programming Language :: Python :: 3.9
Project-URL: Repository, https://github.com/mvaerle/beancount-rabobank
